fport/__init__.py
fport/exceptions.py
fport/policy.py
fport/port.py
fport/protocols.py
fport/session.py
fport/observer/__init__.py
fport/observer/observer.py
fport-1.0.3.dist-info/licenses/LICENSE
fport-1.0.3.dist-info/METADATA
fport-1.0.3.dist-info/WHEEL
fport-1.0.3.dist-info/top_level.txt
fport-1.0.3.dist-info/RECORD
