Metadata-Version: 2.4
Name: fport
Version: 1.0.3
Summary: Loosely-coupled, one-way function wiring for white-box testing and simple add-ons.
Author: minoru_jp
License: MIT License
Project-URL: Homepage, https://github.com/minoru-jp/fport
Project-URL: Source, https://github.com/minoru-jp/fport
Project-URL: Issues, https://github.com/minoru-jp/fport/issues
Keywords: whitebox-testing,testing,observer,add-on,loose-coupling
Classifier: Programming Language :: Python :: 3
Classifier: License :: OSI Approved :: MIT License
Classifier: Development Status :: 3 - Alpha
Classifier: Intended Audience :: Developers
Classifier: Topic :: Software Development :: Testing
Requires-Python: >=3.10
License-File: LICENSE
Dynamic: license-file
